hybridagi/__init__.py
hybridagi/core/__init__.py
hybridagi/core/datatypes.py
hybridagi/core/graph_program.py
hybridagi/core/pipeline.py
hybridagi/embeddings/__init__.py
hybridagi/embeddings/embeddings.py
hybridagi/embeddings/fake.py
hybridagi/embeddings/sentence_transformer.py
hybridagi/loaders/dataset_loader.py
hybridagi/loaders/graph_program_loader.py
hybridagi/memory/__init__.py
hybridagi/memory/document_memory.py
hybridagi/memory/fact_memory.py
hybridagi/memory/integration/__init__.py
hybridagi/memory/integration/falkordb/__init__.py
hybridagi/memory/integration/falkordb/falkordb_document_memory.py
hybridagi/memory/integration/falkordb/falkordb_fact_memory.py
hybridagi/memory/integration/falkordb/falkordb_memory.py
hybridagi/memory/integration/falkordb/falkordb_program_memory.py
hybridagi/memory/integration/falkordb/falkordb_trace_memory.py
hybridagi/memory/integration/local/__init__.py
hybridagi/memory/integration/local/local_document_memory.py
hybridagi/memory/integration/local/local_fact_memory.py
hybridagi/memory/integration/local/local_memory.py
hybridagi/memory/integration/local/local_program_memory.py
hybridagi/memory/integration/local/local_trace_memory.py
hybridagi/memory/program_memory.py
hybridagi/memory/trace_memory.py
hybridagi/metrics/agents/correct_answer.py
hybridagi/metrics/agents/factual_answer.py
hybridagi/metrics/agents/helpful_interaction.py
hybridagi/metrics/documents/documents_similarity.py
hybridagi/metrics/facts/facts_similarity.py
hybridagi/metrics/metric.py
hybridagi/modules/__init__.py
hybridagi/modules/agents/__init__.py
hybridagi/modules/agents/graph_interpreter.py
hybridagi/modules/agents/tools/__init__.py
hybridagi/modules/agents/tools/add_document.py
hybridagi/modules/agents/tools/add_fact.py
hybridagi/modules/agents/tools/add_graph_program.py
hybridagi/modules/agents/tools/ask_user.py
hybridagi/modules/agents/tools/call_graph_program.py
hybridagi/modules/agents/tools/chain_of_thought.py
hybridagi-0.2.4356.dist-info/LICENSE
hybridagi-0.2.4356.dist-info/METADATA
hybridagi-0.2.4356.dist-info/WHEEL
hybridagi-0.2.4356.dist-info/RECORD
